barracudas/__init__.py
barracudas/fysh.py
barracudas-0.0.1.dist-info/METADATA
barracudas-0.0.1.dist-info/WHEEL
barracudas-0.0.1.dist-info/top_level.txt
barracudas-0.0.1.dist-info/RECORD
