Metadata-Version: 2.1
Name: barracudas
Version: 0.0.1
Summary: Micro aquaponics supporting tool kit
Home-page: https://github.com/dasnidm/FYSH
Author: dasnidm
Author-email: dasnidm@gmail.com
License: UNKNOWN
Platform: UNKNOWN
Classifier: Programming Language :: Python :: 3
Classifier: License :: OSI Approved :: MIT License
Classifier: Operating System :: OS Independent
Requires-Python: >=3.6
